setup.cfg
setup.py
creaturecast_rigging/__init__.py
creaturecast_rigging/functions.py
creaturecast_rigging/utilities.py
creaturecast_rigging.egg-info/PKG-INFO
creaturecast_rigging.egg-info/SOURCES.txt
creaturecast_rigging.egg-info/dependency_links.txt
creaturecast_rigging.egg-info/requires.txt
creaturecast_rigging.egg-info/top_level.txt
creaturecast_rigging/biped/__init__.py
creaturecast_rigging/biped/arm.py
creaturecast_rigging/biped/biped.py
creaturecast_rigging/biped/digits.py
creaturecast_rigging/biped/finger.py
creaturecast_rigging/biped/head.py
creaturecast_rigging/biped/ik_foot.py
creaturecast_rigging/biped/ik_leg.py
creaturecast_rigging/biped/ik_limb.py
creaturecast_rigging/biped/leg.py
creaturecast_rigging/biped/limb.py
creaturecast_rigging/biped/neck.py
creaturecast_rigging/biped/shoulder.py
creaturecast_rigging/biped/spine.py
creaturecast_rigging/math/__init__.py
creaturecast_rigging/math/curve.py
creaturecast_rigging/math/matrix.py
creaturecast_rigging/math/vector.py
creaturecast_rigging/math/gameobjects/__init__.py
creaturecast_rigging/math/gameobjects/color.py
creaturecast_rigging/math/gameobjects/gametime.py
creaturecast_rigging/math/gameobjects/grid.py
creaturecast_rigging/math/gameobjects/locals.py
creaturecast_rigging/math/gameobjects/matrix44.py
creaturecast_rigging/math/gameobjects/sphere.py
creaturecast_rigging/math/gameobjects/test_vector3.py
creaturecast_rigging/math/gameobjects/util.py
creaturecast_rigging/math/gameobjects/vector2.py
creaturecast_rigging/math/gameobjects/vector3.py
creaturecast_rigging/nodes/__init__.py
creaturecast_rigging/nodes/attribute.py
creaturecast_rigging/nodes/dag_node.py
creaturecast_rigging/nodes/depend_node.py
creaturecast_rigging/nodes/joint.py
creaturecast_rigging/nodes/layer.py
creaturecast_rigging/nodes/locator.py
creaturecast_rigging/nodes/mesh.py
creaturecast_rigging/nodes/nurbs_curve.py
creaturecast_rigging/nodes/nurbs_surface.py
creaturecast_rigging/nodes/plug.py
creaturecast_rigging/nodes/shader.py
creaturecast_rigging/nodes/skin_cluster.py
creaturecast_rigging/nodes/transform.py
creaturecast_rigging/rigging/__init__.py
creaturecast_rigging/rigging/alembic_node.py
creaturecast_rigging/rigging/body.py
