Metadata-Version: 1.1
Name: creaturecast-rigging
Version: 0.0.8
Summary: Creaturecast rigging api
Home-page: https://github.com/Paxtongerrish/creaturecast_rigging.git
Author: Paxton Gerrish
Author-email: creaturecastlabs@gmail.com
License: UNKNOWN
Keywords: sample setuptools development
Platform: UNKNOWN
Classifier: Development Status :: 3 - Alpha
Classifier: Intended Audience :: End Users/Desktop
Classifier: Topic :: Software Development :: Build Tools
Classifier: License :: OSI Approved :: MIT License
Classifier: Programming Language :: Python :: 2.7
